xiutilities/__init__.py
xiutilities/_version.py
xiutilities/bi_fdr.py
xiutilities/pandas_utils.py
xiutilities/rescore_plots.py
xiutilities/__pycache__/__init__.cpython-310.pyc
xiutilities-1.2.5.post2.dist-info/LICENSE
xiutilities-1.2.5.post2.dist-info/METADATA
xiutilities-1.2.5.post2.dist-info/WHEEL
xiutilities-1.2.5.post2.dist-info/top_level.txt
xiutilities-1.2.5.post2.dist-info/RECORD
