Metadata-Version: 2.2
Name: xiutilities
Version: 1.2.5.post2
Summary: A collection of corss-link mass spectrometry tools.
Home-page: https://github.com/Rappsilber-Laboratory/xiUtils
Author: Falk Boudewijn Schimweg
Author-email: "Falk B. Schimweg" <git@falk.schimweg.de>
License: GNU GENERAL PUBLIC LICENSE
Project-URL: Homepage, https://github.com/Rappsilber-Laboratory/xiUtils
Project-URL: Issues, https://github.com/Rappsilber-Laboratory/xiUtils/issues
Project-URL: Documentation, https://xiutils.readthedocs.io/
Keywords: proteomics,rescoring,crosslink,mass spectrometry
Classifier: Development Status :: 2 - Pre-Alpha
Classifier: Intended Audience :: Developers
Classifier: License :: OSI Approved :: GNU General Public License v3 (GPLv3)
Classifier: Natural Language :: English
Classifier: Programming Language :: Python :: 3
Classifier: Programming Language :: Python :: 3.7
Classifier: Programming Language :: Python :: 3.8
Classifier: Programming Language :: Python :: 3.9
Classifier: Programming Language :: Python :: 3.10
Requires-Python: >=3.7
License-File: LICENSE
Requires-Dist: pandas>=1.3.5
Requires-Dist: numpy>=1.7.2
Requires-Dist: setuptools
Requires-Dist: numpy-indexed>=0.3.7
Requires-Dist: tqdm>=4.66.0
Requires-Dist: pyteomics>=4.6
Requires-Dist: seaborn>=0.11.2
Requires-Dist: pytest
Requires-Dist: pydocstyle
Requires-Dist: pytest-cov
Requires-Dist: pytest-flake8
Requires-Dist: pytest-pydocstyle
Requires-Dist: flake8
Requires-Dist: networkx>=2.6.3
Requires-Dist: multiprocess>=0.70.15
Requires-Dist: deepmerge>=1.1.0
Requires-Dist: scipy>=1.0.1
Requires-Dist: matplotlib>=3.5.3
Requires-Dist: setuptools_scm>=7.1
Dynamic: author
Dynamic: classifier
Dynamic: home-page
Dynamic: requires-dist
Dynamic: requires-python
Dynamic: summary
